testrunner/__init__.py
testrunner/testrunner.py
csse1001_testrunner-1.0.0.dist-info/METADATA
csse1001_testrunner-1.0.0.dist-info/WHEEL
csse1001_testrunner-1.0.0.dist-info/top_level.txt
csse1001_testrunner-1.0.0.dist-info/RECORD
