Metadata-Version: 2.1
Name: csse1001-testrunner
Version: 1.0.0
Summary: Testrunner used for testing in CSSE1001
Home-page: https://github.com/CSSE1001/testrunner
Author: CSSE1001
Author-email: no-reply@uq.edu.au
License: MIT
Platform: UNKNOWN
Classifier: License :: OSI Approved :: MIT License
Classifier: Programming Language :: Python :: 3.9
Requires-Python: >=3.8
